vid2aud/__init__.py
vid2aud/main.py
vid2aud-0.1.1.dist-info/LICENSE
vid2aud-0.1.1.dist-info/METADATA
vid2aud-0.1.1.dist-info/WHEEL
vid2aud-0.1.1.dist-info/top_level.txt
vid2aud-0.1.1.dist-info/RECORD
