Metadata-Version: 2.1
Name: vid2aud
Version: 0.1.1
Summary: A python module to extract audio from a video
Home-page: https://github.com/yijensun/vid2aud
Author: Yi-Jen Sun
Author-email: elainesun442@gmail.com
License: UNKNOWN
Keywords: video,audio,convertion
Platform: UNKNOWN
Classifier: License :: OSI Approved :: MIT License
Classifier: Programming Language :: Python :: 3
Classifier: Operating System :: OS Independent
Requires-Python: >=3.7
License-File: LICENSE
Requires-Dist: ffmpeg-python (>=0.2.0)
Requires-Dist: audioread (>=2.1.9)
Requires-Dist: librosa (>0.8.1)
Requires-Dist: natsort (>=5.5.0)
